aede/__init__.py
aede/simulator.py
aede-0.1.dist-info/DESCRIPTION.rst
aede-0.1.dist-info/METADATA
aede-0.1.dist-info/RECORD
aede-0.1.dist-info/WHEEL
aede-0.1.dist-info/metadata.json
aede-0.1.dist-info/top_level.txt
