Metadata-Version: 2.0
Name: aede
Version: 0.1
Summary: Simulation Package in Genomic
Home-page: https://github.com/BioShock38/aede
Author: Thomas Dias Alves
Author-email: UNKNOWN
License: MIT
Platform: UNKNOWN
